power_digit_addition/__init__.py
power_digit_addition/power_addition.py
power_digit_addition-0.1.0.dist-info/METADATA
power_digit_addition-0.1.0.dist-info/WHEEL
power_digit_addition-0.1.0.dist-info/top_level.txt
power_digit_addition-0.1.0.dist-info/RECORD
